lfm_universal/__init__.py
lfm_universal/engine.py
lfm_universal/forge.py
lfm_universal/physics.py
lfm_universal-5.0.1.dist-info/METADATA
lfm_universal-5.0.1.dist-info/WHEEL
lfm_universal-5.0.1.dist-info/top_level.txt
lfm_universal-5.0.1.dist-info/RECORD
