Metadata-Version: 2.4
Name: lfm-universal
Version: 5.0.1
Summary: LFM V5.0 - Physics-Based Inference & Geometric Pruning Engine
Author: Keith Luton
Author-email: keith@thenewfaithchurch.org
Classifier: Programming Language :: Python :: 3
Classifier: License :: Other/Proprietary License
Classifier: Operating System :: OS Independent
Requires-Python: >=3.7
Requires-Dist: torch>=2.0.0
Requires-Dist: transformers>=4.30.0
Requires-Dist: accelerate>=0.20.0
Dynamic: author
Dynamic: author-email
Dynamic: classifier
Dynamic: description
Dynamic: description-content-type
Dynamic: requires-dist
Dynamic: requires-python
Dynamic: summary
